{
    "call": {
        "title": "ການ ສູນ ໂທ Nuri",
        "subtitle" : "ຂໍ້ມູນ ທີ່ຈໍາເປັນ ສໍາລັບການ ດໍາລົງຊີວິດ ຢູ່ໃນເກົາຫລີ , ຂໍ້ມູນຂ່າວສານ , ອົງການຈັດຕັ້ງ ສະຫນອງ ການເຊື່ອມຕໍ່ , ການສະຫນອງ ດັ່ງກ່າວເປັນ ການບໍລິການ ຕີລາຄາ ດໍາລົງຊີວິດ ຢູ່ໃນ 13 ພາສາ",
        "phone" : "1577 - 1366"
    },
    "help": {
            "title": "ຊ່ວຍເຫຼືອ ທີ່ໄດ້ຮັບ ການ",
            "text1": "ວັດທະນະທໍາ ສູນກາງ ສະຫນັບສະຫນູນ ຄອບຄົວ",
            "text2": "ຂໍ້ມູນ ຕິດຕໍ່ສຸກເສີນ"
    },
    "guidebook": "ຄູ່ມືການສອນ ສໍາລັບການ ດໍາລົງຊີວິດ ຢູ່ໃນເກົາຫລີ"
}